LICENSE.txt
MANIFEST.in
README.txt
setup.py
MayLeaSports.egg-info/PKG-INFO
MayLeaSports.egg-info/SOURCES.txt
MayLeaSports.egg-info/dependency_links.txt
MayLeaSports.egg-info/top_level.txt
folder/__init__.py