Metadata-Version: 2.1
Name: MayLeaSports
Version: 0.0.1
Summary: Pakcage for sports teams and leagues
Home-page: 
Author: Sam Johnson
Author-email: samjj02@gmail.com
License: MIT
Classifier: Development Status :: 5 - Production/Stable
Classifier: Intended Audience :: Developers
Classifier: Operating System :: OS Independent
Classifier: License :: OSI Approved :: MIT License
Classifier: Programming Language :: Python :: 3.11
License-File: LICENSE.txt
